mtinfo/__init__.py
mtinfo/arg.py
mtinfo/cache.py
mtinfo/data.py
mtinfo/debug.py
mtinfo/helpers.py
mtinfo/irc.py
mtinfo/istor_schema.py
mtinfo/loader.py
mtinfo/logging.py
mtinfo/misc.py
mtinfo/tvmaze/__init__.py
mtinfo/tvmaze/helpers.py
mtinfo/tvmaze/irc.py
mtinfo/tvmaze/main.py
mtinfo/tvmaze/run.py
mtinfo/tvmaze/tvmaze.py
mtinfo/tvmaze/tests/__init__.py
mtinfo/tvmaze/tests/generic.py
mtinfo-0.2.4.dist-info/METADATA
mtinfo-0.2.4.dist-info/RECORD
mtinfo-0.2.4.dist-info/WHEEL
mtinfo-0.2.4.dist-info/entry_points.txt
mtinfo-0.2.4.dist-info/top_level.txt
