Metadata-Version: 2.1
Name: mtinfo
Version: 0.2.4
Summary: TVmaze/iMDB API Interface
Home-page: https://github.com/nixnodes/mtinfo
Author: nixnodes
Author-email: io@nixnodes.net
License: MIT
Platform: UNKNOWN
Classifier: Programming Language :: Python :: 3
Classifier: License :: OSI Approved :: MIT License
Classifier: Operating System :: OS Independent
Requires-Dist: requests
Requires-Dist: pydle
Requires-Dist: coloredlogs; "linux" in sys_platform
